darkslide/__init__.py
darkslide/__main__.py
darkslide/cli.py
darkslide/generator.py
darkslide/macro.py
darkslide/parser.py
darkslide/rst.py
darkslide/utils.py
darkslide/watcher.py
darkslide/mods/wide16x9/css/mod.css
darkslide/themes/abyss/css/theme.css
darkslide/themes/default/template.html
darkslide/themes/default/css/base.css
darkslide/themes/default/css/print.css
darkslide/themes/default/css/screen.css
darkslide/themes/default/css/theme.css
darkslide/themes/default/js/slides.js
darkslide/themes/void/css/theme.css
darkslide/themes/white/css/theme.css
darkslide-6.0.0.dist-info/LICENSE
darkslide-6.0.0.dist-info/METADATA
darkslide-6.0.0.dist-info/WHEEL
darkslide-6.0.0.dist-info/entry_points.txt
darkslide-6.0.0.dist-info/top_level.txt
darkslide-6.0.0.dist-info/RECORD
