Metadata-Version: 2.1
Name: darkslide
Version: 6.0.0
Summary: Lightweight markup language-based html5 slideshow generator. Forked from Landslide.
Home-page: https://github.com/ionelmc/python-darkslide
Author: Adam Zapletal
Author-email: adamzap@gmail.com
Maintainer: Ionel Cristian Mărieș
Maintainer-email: contact@ionelmc.ro
License: Apache-2.0
Project-URL: Changelog, https://github.com/ionelmc/python-darkslide/blob/master/CHANGELOG.rst
Project-URL: Issue Tracker, https://github.com/ionelmc/python-darkslide/issues
Keywords: markdown,slideshow,presentation,rst,restructuredtext,textile,landslide
Platform: any
Classifier: Development Status :: 5 - Production/Stable
Classifier: Intended Audience :: Developers
Classifier: License :: OSI Approved :: Apache Software License
Classifier: Operating System :: Unix
Classifier: Operating System :: POSIX
Classifier: Operating System :: Microsoft :: Windows
Classifier: Programming Language :: Python
Classifier: Programming Language :: Python :: 2.7
Classifier: Programming Language :: Python :: 3
Classifier: Programming Language :: Python :: 3.7
Classifier: Programming Language :: Python :: 3.8
Classifier: Programming Language :: Python :: Implementation :: CPython
Classifier: Programming Language :: Python :: Implementation :: PyPy
Classifier: Topic :: Utilities
Requires-Python: >=2.7, !=3.0.*, !=3.1.*, !=3.2.*, !=3.3.*
Requires-Dist: Jinja2
Requires-Dist: Markdown
Requires-Dist: Pygments
Requires-Dist: docutils
Requires-Dist: six
Requires-Dist: qrcode
